{
    "en": {
        "lvl_mode": "Mode",
        "lvl_mode_auto": "Smart Scan (Automatic Optimization)",
        "lvl_mode_manual": "Manual Window",
        "lvl_min": "Lower Limit (Hz)",
        "lvl_max": "Upper Limit (Hz)",
        "lvl_target_db": "Target Level (dB)",
        "lvl_manual_help": "Set the desired sound pressure level for the fitted range.",
        "lvl_min_help_auto": "Start of Smart Scan search range",
        "lvl_max_help_auto": "End of Smart Scan search range",
        "lvl_min_help_manual": "Manual fitting lower limit",
        "lvl_max_help_manual": "Manual fitting upper limit",
        "filter_smooth": "Filtter smoothing",
        "trans_width": "The width of the frequency range where the correction tapers to zero (recommended 50-200 Hz)." ,
        "enable_tdc": "Temporal Decay Control (TDC)",
        "tdc_strength": "TDC Strength (0-100%)",
        "tdc_help": "Reduces the ringing time (decay) of resonances. Very effective for room modes",
        "guide_tdc_title": "⏳ Guide: Temporal Decay Control",
        "guide_tdc_body": "**TDC** is a time-domain correction.\n- **How it works:** It creates an inverted impulse that cancels the room's tail (ringing).\n- **Benefit:** Bass doesn't just get quieter, it *stops* faster. Impact sounds become much tighter.",
        "enable_afdw": "Enable Adaptive FDW",
        "afdw_help": "Automatically adjusts windowing based on measurement reliability. Recommended setting.",
        "guide_afdw_title": "🧠 Guide: Adaptive FDW (A-FDW)",
        "guide_afdw_body": "**Adaptive FDW** is an intelligent windowing method.\n\n- **Why:** It protects the filter from errors. If the measurement is uncertain (e.g., a sharp dip), A-FDW immediately reduces the window length.\n- **Benefit:** More natural treble and punchier bass, because the engine doesn't try to correct acoustic noise.",
        "ir_matala": "Minimum 0ms",
        "ir_korkea": "Maximum 1000ms",
        "saved_local": "Saved locally:",
        "done_msg": "Analysis Complete.",
        "stat_calc": "Calculating...",
        "stat_reading": "Reading...",
        "stat_plot": "Plotting...",
        "stat_done": "Done!",
        "err_file_not_found": "File not found:",
        "err_missing_file": "Error: Files missing.",
        "err_parse": "Parse error.",
        "err_upload_custom": "Missing Custom HC file.",
        "err_inv_custom": "Invalid HC file.",
        "yaml_title": "CamillaDSP Config",
        "rep_header": "--- CALCULATION REPORT ---",
        "rep_corr_status": "Correction Enabled:",
        "rep_corr_range": "Correction Range:",
        "rep_lvl_mode": "Level Mode:",
        "rep_lvl_range": "Auto-Calc Range:",
        "rep_target_lvl": "Target Level:",
        "rep_offset": "Applied Offset:",
        "rep_norm": "Normalization:",
        "rep_align": "Time Alignment:",
        "rep_peak": "Peak before norm:",
        "rep_fdw": "FDW Used:", 
        "rep_yes": "YES",
        "rep_no": "NO",
        "rep_norm_done": "DONE (-1.0 dB)",
        "rep_norm_skip": "NO (Signal was Safe)",
        "rep_disabled": "DISABLED",
        "rep_multi": "Multi-Rate Generation:",
        "rep_reg": "Regularization Strength:",
        "valid_pos": "Must be positive",
        "valid_freq": "Invalid frequency",
        "ir_window": "IR Window (ms)",
        "ir_window_help": "Window length for Minimum Phase calculation.",
        "phase_limit": "Phase Corr Limit (Hz)",
        "phase_limit_help": "Max frequency for phase correction.",
        "title": "CamillaFIR",
        "subtitle": "By VilhoValittu & GeminiPro",
        "grp_settings": "Settings & Files",
        "upload_l": "Measurement L (.txt)",
        "upload_r": "Measurement R (.txt)",
        "path_l": "OR Local Path L",
        "path_r": "OR Local Path R",
        "path_help": "Paste full path (e.g. C:\\Audio\\L.txt).",
        "ph_l": "Select Left .txt",
        "ph_r": "Select Right .txt",
        "fs": "Base Sample Rate",
        "fs_help": "Sample rate used in filter.",
        "taps": "Base Taps",
        "taps_help": "Filter length. Higher = better bass resolution but more latency.",
        "filter_type": "Filter Type",
        "ft_linear": "Linear Phase",
        "ft_min": "Minimum Phase",
        "ft_mixed": "Mixed Phase",
        "ft_help": "Phase handling strategy. Linear=Timing, Min=No pre-ringing, Mixed=Best of both. Asymmetric Linear=Time windowed linear filter",
        "mixed_freq": "Mixed Phase Split (Hz)",
        "mixed_freq_help": "Frequency splitting Linear (low) and Minimum (high) phase.",
        "gain": "Gain (dB)",
        "gain_help": "Global output volume adjustment.",
        "smooth_type": "Smoothing",
        "smooth_help": "Standard uses fixed octave bands. Psychoacoustic mimics human hearing perception.",
        "smooth_std": "Standard 1/48",
        "smooth_psy": "Psychoacoustic",
        "fdw": "FDW Cycles",
        "fdw_help": "Frequency Dependent Windowing. Standard: 15. Lower focuses on direct sound.",
        "hc_mode": "Target Curve",
        "hc_mode_help": "Select the target frequency response curve.",
        "hc_harman": "Harman (Standard +6dB)",
        "hc_harman8": "Harman (+8dB Bass)",
        "hc_toole": "Dr. Toole (Gentle Tilt)",
        "hc_bk": "B&K 1974",
        "hc_flat": "Flat",
        "hc_cinema": "Cinema X-Curve",
        "hc_mode_upload": "Upload Custom...",
        "hc_custom": "Custom Target File",
        "hc_custom_help": "Required if 'Upload Custom...' is selected.",
        "hc_range_help": "Frequency range where magnitude correction is active.",
        "corr_mode": "Correction",
        "enable_corr": "Enable Correction",
        "min_freq": "Correction Min (Hz)",
        "max_freq": "Correction Max (Hz)",
        "reg_strength": "Regularization (dB)",
        "reg_help": "Limits how much the filter tries to boost deep nulls. 30-50dB recommended.",
        "lvl_mode": "Level Match Mode",
        "lvl_mode_help": "How the filter is aligned to measurement level.",
        "lvl_auto": "Automatic",
        "lvl_man": "Manual dB",
        "lvl_target_db": "Manual Target (dB)",
        "lvl_manual_help": "Target level in dB if Manual mode is selected.",
        "lvl_algo": "Algo",
        "algo_mean": "Average",
        "algo_median": "Median",
        "lvl_min": "Range Min (Hz)",
        "lvl_max": "Range Max (Hz)",
        "lvl_help": "Freq range for level matching.",
        "norm_opt": "Normalize Output", 
        "enable_norm": "Normalize to -1.0 dB",
        "norm_help": "Ensures filter peak does not exceed -1.0 dBFS.",
        "stereo_link": "Stereo Link",
        "enable_link": "Stereo Link (Preserve Balance)",
        "link_help": "Applies same gain offset to both channels to keep stereo image.",
        "align_opt": "Time Alignment",
        "enable_align": "Auto-Align L/R",
        "align_help": "Aligns impulse peaks of L and R channels.",
        "exc_prot": "Excursion Protection",
        "enable_exc": "Enable Excursion Protection",
        "exc_freq": "Protection Freq (Hz)",
        "exc_help": "Prevents bass boost below this frequency (e.g. port tuning).",
        "max_boost": "Max Boost (dB)",
        "max_boost_help": "Maximum allowed boost. Hard limit 8dB.",
        "hpf": "HPF (Subsonic)",
        "hpf_enable": "Enable HPF",
        "hpf_freq": "HPF Freq (Hz)",
        "hpf_freq_help": "High Pass Filter to protect woofers.",
        "hpf_slope": "HPF Slope",
        "xo_freq": "Freq (Hz)",
        "xo_slope": "Slope (dB/oct)",
        "xo_slope_help": "Steepness of the crossover (acoustic slope).",
        "xo_help": "Linearize existing crossovers.",
        "fmt": "Format",
        "layout": "Layout",
        "layout_mono": "Mono",
        "layout_stereo": "Stereo",
        "multi_rate": "Generate All Rates",
        "multi_rate_help": "Generates filters for 44.1k, 48k, 88.2k, 96k, 176.4k, 192k.",
        "xo_title": "Crossover Linearization",
        "xo_1": "Crossover 1", "xo_2": "Crossover 2", "xo_3": "Crossover 3", "xo_4": "Crossover 4", "xo_5": "Crossover 5",
        "lvl_algo_help": "Median is recommended (ignores peaks/dips).",
        "fmt_help": "Format of filter",
        "fmt_wav": "WAV (.wav)", "fmt_bin": "Raw Binary (.bin)", "fmt_txt": "Text (.txt)",
        "sigmastudio_help": "How to use with SigmaStudio:",
        "sigmastudio_step1": "1. Set Format to 'Raw Binary'.",
        "sigmastudio_step2": "2. Use 'External FIR' cell in SigmaStudio.",
        "sigmastudio_step3": "3. Point to the generated .bin file.",
        "report_header": "CamillaFIR Generation Report",
        "report_stats": "Final Statistics",
        "report_conf": "Acoustic Intelligence Confidence",
        "report_events": "Detected Acoustic Events",
        "tab_files": "1. Files", "tab_basic": "2. Basic", "tab_target": "3. Target", "tab_adv": "4. Advanced", "tab_xo": "5. XO", "tab_guides": "6. Guides",
        "guide_taps_title": "❓ Guide: Taps & Resolution",
        "guide_taps_body": "**Taps** represent the length of the FIR filter.\n\n- **Resolution:** More taps allow the filter to target very narrow resonances in the low bass region.\n- **Latency:** In Linear Phase, latency is half the tap count. At 44.1kHz, 65k taps = ~740ms delay.\n- **Recommendation:** Use 65,536 or 131,072 for critical listening.",
        "guide_ft_title": "❓ Guide: Filter Types",
        "guide_ft_body": "**1. Linear Phase:** Corrects both magnitude and phase. Best timing and tight bass, but high latency.\n**2. Minimum Phase:** Zero latency. Corrects magnitude only. No pre-ringing, ideal for Gaming/TV.\n**3. Mixed Phase:** Uses Linear Phase for bass (<300Hz) and Minimum Phase for highs.\n**4. Asymmetric Linear:** Hybrid mode for low latency phase correction.",
        "guide_sigma_title": "❓ Guide: Sigma Smoothing",
        "guide_sigma_body": "Advanced smoothing that dynamically follows the measurement confidence. It smooths more where data is noisy and less where it is precise.",
        "guide_mix_title": "❓ Guide: Mixed Phase Details",
        "guide_mix_body": "Mixed Phase applies Linear Phase only to low frequencies.\n- **300 Hz (Default):** Corrects primary room modes without affecting vocal clarity.\n- **500+ Hz:** Tightens mid-bass impact, but might affect high-frequency transients.",
        "guide_fdw_title": "❓ Guide: FDW Cycles",
        "guide_fdw_body": "**Frequency Dependent Windowing** determines how much room influence is corrected.\n- **15 Cycles:** Standard HiFi balance.\n- **Lower (e.g. 5-8):** Focuses on speakers' direct sound.\n- **Higher (25+):** Aggressive room correction.",
        "guide_reg_title": "❓ Guide: Regularization",
        "guide_reg_body": "Regularization prevents the filter from over-boosting sharp nulls. This keeps the correction natural and prevents speaker damage.",
        "guide_lvl_title": "❓ Guide: Leveling",
        "guide_lvl_body": "Ensures the filter gain matches your target volume level. Median algorithm is best for ignoring extreme room reflections.",
        "guide_sl_title": "❓ Guide: Stereo Link",
        "guide_sl_body": "Applies identical gain to both channels to preserve the original stereo balance (phantom center).",
        "guide_ep_title": "❓ Guide: Excursion Protection",
        "guide_ep_body": "Protects small woofers by limiting boost below the port tuning or driver limits.",
        "guide_asy_title": "🚀 Asymmetric Linear (NEW)",
        "guide_asy_body": "**Asymmetric Linear** offers linear phase benefits with minimal delay.\n- **Left Window (100ms):** Controls pre-ringing. Keeps transients sharp.\n- **Right Window (500ms):** Provides enough resolution for deep bass cleaning.\n- **Benefit:** Best for movies and gaming.",
        "guide_ai_title": "🧠 Acoustic Intelligence",
        "guide_ai_body": "**Acoustic Intelligence** (v2.6.2) analyzes room acoustics automatically.\n- **Confidence:** Aim for >85%. Low values suggest high background noise.\n- **Events:** Distinguishes between standing waves (Resonance) and bounces (Reflection).",
        "guide_summary_title": "📝 How to read Summary.txt",
        "guide_summary_body": "- **Error (ms):** How long a frequency rings. >300ms is a critical room mode.\n- **Distance (m):** Path length of a reflection (e.g. 13m = back wall bounce).\n- **Markers:** Specifically targeted frequencies for acoustic cleaning."
    },
    
    "fi": {
        "lvl_mode": "Tila",
        "lvl_mode_auto": "Smart Scan (Automaattinen optimointi)",
        "lvl_mode_manual": "Manuaalinen ikkuna",
        "lvl_min": "Alaraja (Hz)",
        "lvl_max": "Yläraja (Hz)",
        "lvl_target_db": "Tavoitetaso (dB)",
        "lvl_manual_help": "Aseta tavoiteltu äänenpainetaso sovittua aluetta varten.",
        "lvl_min_help_auto": "Smart Scanin hakualueen alku",
        "lvl_max_help_auto": "Smart Scanin hakualueen loppu",
        "lvl_min_help_manual": "Manuaalisen sovituksen alaraja",
        "lvl_max_help_manual": "Manuaalisen sovituksen yläraja",
        "trans_width": "Kuinka leveällä alueella korjaus vaimenee nollaan (suositus 50-200 Hz)." ,
        "enable_tdc": "Resonanssin ajallinen vaimennus (TDC)",
        "tdc_strength": "TDC Voimakkuus (0-100%)",
        "tdc_help": "Vähentää resonanssien sointiaikaa (decay). Erittäin tehokas huonemoodeihin.",
        "guide_tdc_title": "⏳ Opas: Temporal Decay Control",
        "guide_tdc_body": "**TDC** on aikatasokorjaus.\n- **Miten se toimii:** Se luo käänteisen impulssin, joka kumoaa huoneen jälkisoinnin.\n- **Hyöty:** Basso ei vain hiljene, vaan se *pysähtyy* nopeammin. Iskuäänet muuttuvat paljon tiukemmiksi.",
        "enable_afdw": "Käytä adaptiivista FDW:tä",
        "afdw_help": "Säätää ikkunointia automaattisesti mittauksen luotettavuuden mukaan. Suositeltu asetus.",
        "guide_afdw_title": "🧠 Opas: Adaptiivinen FDW (A-FDW)",
        "guide_afdw_body": "**Adaptiivinen FDW** on älykäs ikkunointimenetelmä.\n\n- **Miksi:** Se suojaa suodatinta virheiltä. Jos mittaus on epävarma (esim. kapea vaimentuma), A-FDW pienentää ikkunaa välittömästi.\n- **Hyöty:** Luonnollisempi diskantti ja iskevämpi basso, koska moottori ei yritä korjata akustista kohinaa.",
        "xo_slope_help": "Jakosuotimen akustinen jyrkkyys (esim. 2. aste = 12dB).",
        "xo_freq_help": "Jakotaajuus, jonka vaihevaste halutaan oikaista.",
        "ir_matala": "Minimi 0ms",
        "ir_korkea": "Maksimi 1000ms",
        "phase_limit": "Vaihekorjauksen yläraja (Hz)",
        "phase_limit_help": "Taajuus, johon asti vaihevirhettä korjataan.",
        "rep_header": "--- LASKENTARAPORTTI ---",
        "rep_corr_status": "Korjaus päällä:",
        "rep_corr_range": "Korjausalue:",
        "rep_lvl_mode": "Tason laskenta:",
        "rep_lvl_range": "Laskenta-alue:",
        "rep_target_lvl": "Tavoitetaso:",
        "rep_offset": "Tason muutos:",
        "rep_norm": "Normalisointi:",
        "rep_align": "Aika-ajoitus:",
        "rep_peak": "Huippu ennen norm:",
        "rep_fdw": "FDW Käytössä:", 
        "rep_yes": "KYLLÄ",
        "rep_no": "EI",
        "rep_norm_done": "TEHTY (-1.0 dB)",
        "rep_norm_skip": "EI (Taso oli turvallinen)",
        "rep_disabled": "POIS PÄÄLTÄ",
        "rep_multi": "Multi-Rate Vienti:",
        "rep_reg": "Regularization:",
        "yaml_title": "CamillaDSP Konfiguraatio",
        "err_missing_file": "Virhe: Tiedostot puuttuu.",
        "err_file_not_found": "Tiedostoa ei löydy:",
        "err_parse": "Lukuvirhe.",
        "err_upload_custom": "HC-tiedosto puuttuu.",
        "err_inv_custom": "Viallinen HC-tiedosto.",
        "err_plot": "Piirto epäonnistui.",
        "stat_reading": "Luetaan...",
        "stat_calc": "Lasketaan...",
        "stat_plot": "Piirretään...",
        "stat_done": "Valmis!",
        "done_msg": "Analyysi valmis.",
        "saved_local": "Tallennettu kansioon:",
        "title": "CamillaFIR",
        "subtitle": "VilhoValittu & GeminiPro",
        "grp_settings": "Asetukset & Tiedostot",
        "upload_l": "Mittaus L (.txt)",
        "upload_r": "Mittaus R (.txt)",
        "path_l": "TAI paikallinen polku L",
        "path_r": "TAI paikallinen polku R",
        "path_help": "Liitä koko polku (esim. C:\\Audio\\L.txt).",
        "ph_l": "Valitse vasen .txt",
        "ph_r": "Valitse oikea .txt",
        "fs": "Näytetaajuus (Hz)",
        "fs_help": "Käytettävä näytetaajuus.",
        "taps": "Tap-määrä",
        "taps_help": "Filtterin pituus. Enemmän = parempi basso, mutta suurempi viive.",
        "filter_type": "Suodintyyppi",
        "ft_linear": "Linear Phase",
        "ft_min": "Minimum Phase",
        "ft_mixed": "Mixed Phase",
        "ft_asymmetric": "Asymmetric Linear",
        "ft_help": "Vaiheen käsittelytapa. Linear=Ajoitus, Min=Ei esisointia, Mixed=Paras molemmista. Asymmetric Linear = Imitoi REWstä saatavaa aikaikkunoitua filtteriä",
        "mixed_freq": "Mixed Phase Jakotaajuus (Hz)",
        "mixed_freq_help": "Taajuus, joka jakaa Linear (basso) ja Minimum (diskantti) vaiheet.",
        "gain": "Vahvistus (dB)",
        "gain_help": "Yleinen ulostulotason säätö.",
        "smooth_type": "Tasoitus",
        "smooth_help": "Standardi käyttää kiinteitä oktaavikaistoja. Psykoakustinen jäljittelee kuuloa.",
        "smooth_std": "Standardi 1/48",
        "smooth_psy": "Psykoakustinen",
        "fdw": "FDW-syklit",
        "fdw_help": "Taajuusriippuva ikkunointi. Vakio: 15. Pienempi arvo painottaa suoraa ääntä.",
        "hc_mode": "Tavoitekäyrä",
        "hc_mode_help": "Valitse haluttu taajuusvastetavoite.",
        "hc_harman": "Harman (Vakio +6dB)",
        "hc_harman8": "Harman (+8dB Basso)",
        "hc_toole": "Dr. Toole (Loiva kallistus)",
        "hc_bk": "B&K 1974",
        "hc_flat": "Suora (Flat)",
        "hc_cinema": "Cinema X-Curve",
        "hc_mode_upload": "Lataa oma...",
        "hc_custom": "Oma tavoitetiedosto",
        "hc_custom_help": "Tarvitaan jos 'Lataa oma...' on valittu.",
        "hc_range_help": "Taajuusalue, jolla magnitudikorjaus on aktiivinen.",
        "corr_mode": "Korjaus",
        "enable_corr": "Käytä EQta",
        "min_freq": "Korjaus Min (Hz)",
        "max_freq": "Korjaus Max (Hz)",
        "reg_strength": "Regularisointi (dB)",
        "reg_help": "Estää kapeiden kuoppien ylikorjaamisen. 30-50dB suositeltu.",
        "lvl_mode": "Tason täsmäys",
        "lvl_mode_help": "Miten suodin sovitetaan mittauksen tasoon.",
        "lvl_auto": "Automaattinen",
        "lvl_man": "Manuaalinen dB",
        "lvl_target_db": "Tavoitetaso (dB)",
        "lvl_manual_help": "Tavoitetaso dB:nä jos Manuaalinen valittu.",
        "lvl_algo": "Algoritmi",
        "algo_mean": "Keskiarvo",
        "algo_median": "Mediaani",
        "lvl_min": "Alue Min (Hz)",
        "lvl_max": "Alue Max (Hz)",
        "lvl_help": "Taajuusalue tason täsmäykseen.",
        "norm_opt": "Normalisointi",
        "enable_norm": "Normalisoi -1.0 dB",
        "norm_help": "Varmistaa ettei suotimen huippu ylitä -1.0 dBFS.",
        "stereo_link": "Stereo Link",
        "enable_link": "Linkitä kanavat (Säilytä balanssi)",
        "link_help": "Käyttää samaa vahvistusta molempiin kanaviin stereokuvan säilyttämiseksi.",
        "align_opt": "Aikaviive",
        "enable_align": "Automaattinen ajoitus L/R",
        "align_help": "Kohdistaa impulssihuiput molemmissa kanavissa.",
        "exc_prot": "Bassoelementin suojaus",
        "enable_exc": "Käytä suojausta",
        "exc_freq": "Suojataajuus (Hz)",
        "exc_help": "Estää basson korostuksen tämän alapuolella.",
        "max_boost": "Maksimikorostus (dB)",
        "max_boost_help": "Suurin sallittu suodattimen boost. Raja 8dB.",
        "hpf": "HPF (Subsonic)",
        "hpf_enable": "Käytä HPF",
        "hpf_freq": "HPF Taajuus (Hz)",
        "hpf_freq_help": "Ylipäästösuodin elementtien suojaksi.",
        "hpf_slope": "HPF Jyrkkyys",
        "xo_freq": "Taajuus (Hz)",
        "xo_slope": "Jyrkkyys (dB/oct)",
        "xo_help": "Linearisoi olemassa olevat jakosuotimet.",
        "fmt": "Muoto",
        "layout": "Asettelu",
        "layout_mono": "Mono",
        "layout_stereo": "Stereo",
        "multi_rate": "Luo kaikki yleisimmät suodin-taajuudet",
        "multi_rate_help": "Luo suotimet taajuuksille 44.1k - 192k.",
        "xo_title": "Jakosuotimien linearisointi",
        "xo_1": "Jakosuodin 1", "xo_2": "Jakosuodin 2", "xo_3": "Jakosuodin 3", "xo_4": "Jakosuodin 4", "xo_5": "Jakosuodin 5",
        "filter_smooth": "Filtterin tasoitus",
        "lvl_algo_help": "Mediaani on suositeltu (hylkää piikit/kuopat).",
        "fmt_help": "Filtterin formaatti",
        "fmt_wav": "WAV (.wav)", "fmt_bin": "Raaka binääri (.bin)", "fmt_txt": "Teksti (.txt)",
        "sigmastudio_help": "Käyttö SigmaStudion kanssa:",
        "sigmastudio_step1": "1. Valitse muodoksi 'Raaka binääri'.",
        "sigmastudio_step2": "2. Käytä 'External FIR' -lohkoa SigmaStudiossa.",
        "sigmastudio_step3": "3. Osoita generoituun .bin tiedostoon.",
        "report_header": "CamillaFIR Generointiraportti",
        "report_stats": "Lopulliset tilastot",
        "report_conf": "Acoustic Intelligence Luottamus",
        "report_events": "Havaitut akustiset tapahtumat",
        "tab_files": "1. Tiedostot", "tab_basic": "2. Perus", "tab_target": "3. Tavoite", "tab_adv": "4. Edistyneet", "tab_xo": "5. XO", "tab_guides": "6. Oppaat",
        "guide_taps_title": "❓ Opas: Tapit & Resoluutio",
        "guide_taps_body": "**Tap-määrä** määrittää FIR-suodattimen pituuden ja tarkkuuden.\n\n- **Resoluutio:** Enemmän tapseja mahdollistaa kapeiden huonemoodien korjaamisen bassotaajuuksilla.\n- **Viive:** Linear Phase -tilassa viive on tasan puolet tap-määrästä. 44.1kHz nopeudella 65k tapseja = ~740ms viive.\n- **Suositus:** 65 536 tai 131 072 parasta laatua haettaessa.",
        "guide_ft_title": "❓ Opas: Suodintyypit",
        "guide_ft_body": "**1. Linear Phase:** Korjaa vasteen ja vaiheen (ajoituksen). Paras hifistelyyn, mutta suuri viive.\n**2. Minimum Phase:** Nollaviive. Korjaa vain vasteen. Ei esisointia, paras peleihin ja TV:hen.\n**3. Mixed Phase:** Käyttää lineaarivaihetta bassoille (<300Hz) ja minimivaihetta diskanteille.\n**4. Asymmetric Linear:** Hybridi matalan viiveen vaihekorjaukseen.",
        "guide_sigma_title": "❓ Opas: Sigma-tasoitus",
        "guide_sigma_body": "Edistynyt tasoitus, joka seuraa dynaamisesti mittauksen luotettavuutta. Se tasoittaa enemmän epäluotettavissa kohdissa ja säilyttää tarkkuuden puhtaassa datassa.",
        "guide_mix_title": "❓ Opas: Mixed Phase -yksityiskohdat",
        "guide_mix_body": "Mixed Phase käyttää lineaarivaihetta vain matalilla taajuuksilla.\n- **300 Hz (Oletus):** Korjaa huonemoodit vaikuttamatta laulun selkeyteen.\n- **500+ Hz:** Napakoittaa iskuääniä (mid-bass), mutta voi vaikuttaa diskantin vaihekoherenssiin.",
        "guide_fdw_title": "❓ Opas: FDW-ikkunointi",
        "guide_fdw_body": "**FDW** (Frequency Dependent Windowing) määrittää kuinka suuri osa huoneen heijastuksista korjataan.\n- **15 Sykliä:** Vakioasetus hifikuunteluun.\n- **Pienempi (esim. 5-8):** Keskittyy kaiuttimen suoraan ääneen.\n- **Suurempi (25+):** Aggressiivinen huonekorjaus.",
        "guide_reg_title": "❓ Opas: Regularisointi",
        "guide_reg_body": "Regularisointi estää suodatinta ylikorjaamasta kapeita vaimentumia. Tämä pitää äänen luonnollisena ja estää elementtien vaurioitumisen.",
        "guide_lvl_title": "❓ Opas: Tason täsmäys",
        "guide_lvl_body": "Varmistaa, että suotimen vahvistus vastaa tavoitevoimakkuutta. Mediaani-algoritmi on paras sivuuttamaan huoneheijastusten aiheuttamat äärimmäiset piikit.",
        "guide_sl_title": "❓ Opas: Stereo Link",
        "guide_sl_body": "Asettaa molemmille kanaville saman vahvistusmuutoksen, jotta alkuperäinen stereotasapaino (phantom center) säilyy.",
        "guide_ep_title": "❓ Opas: Ekskursiosuojaus",
        "guide_ep_body": "Suojaa kaiuttimia rajoittamalla korostusta erittäin matalilla taajuuksilla (esim. refleksivirityksen alapuolella).",
        "guide_asy_title": "🚀 Asymmetric Linear (UUTTA)",
        "guide_asy_body": "**Asymmetric Linear** tarjoaa lineaarivaiheen edut lähes ilman viivettä.\n- **Vasen ikkuna (100ms):** Hallitsee esisointia. Iskuäänet säilyvät terävinä.\n- **Oikea ikkuna (500ms):** Riittävä resoluutio syvään basson puhdistukseen.\n- **Hyöty:** Paras valinta videoille ja musiikille.",
        "guide_ai_title": "🧠 Acoustic Intelligence",
        "guide_ai_body": "**Acoustic Intelligence** analysoi huoneen akustiikan automaattisesti.\n- **Luottamus:** Tavoittele >85%. Matala arvo kertoo liiallisesta taustahälystä.\n- **Tapahtumat:** Erottaa seisovat aallot (Resonanssi) ja heijastukset (Reflection).",
        "guide_summary_title": "📝 Summary-raportin lukuohje",
        "guide_summary_body": "- **Virhe (ms):** Resonanssin kesto. Yli 300ms on kriittinen huonemoodi.\n- **Etäisyys (m):** Heijastuksen matka (esim. 13m = takaseinäheijastus).\n- **Merkit:** Taajuudet, joihin on kohdistettu syvä akustinen puhdistus."
    }
}
